[{"id":"535e5e50.e4b33","type":"tab","label":"Forward_IoF_Config"},{"id":"a6dd8212.fbf47","type":"mqtt-broker","z":"","broker":"iot.eclipse.org","port":"1883","clientid":"","usetls":false,"compatmode":true,"keepalive":"60","cleansession":true,"willTopic":"","willQos":"0","willPayload":"","birthTopic":"","birthQos":"0","birthPayload":""},{"id":"25b1b77f.913cf8","type":"mqtt in","z":"535e5e50.e4b33","name":"IoF Config","topic":"iof/config","qos":"0","broker":"a6dd8212.fbf47","x":119,"y":225,"wires":[["6c8fdc82.2fe42c","4010ba63.642924"]]},{"id":"534ecd7b.28ede4","type":"debug","z":"535e5e50.e4b33","name":"Debug message","active":true,"console":"true","complete":"true","x":817,"y":221,"wires":[]},{"id":"6c8fdc82.2fe42c","type":"http request","z":"535e5e50.e4b33","name":"Publish to iof.c0d3r.ch","method":"GET","ret":"txt","url":"https://iof.c0d3r.ch/api/configuration/{{payload}}","tls":"","x":451.5,"y":224,"wires":[["534ecd7b.28ede4"]]},{"id":"4010ba63.642924","type":"http request","z":"535e5e50.e4b33","name":"Publish to iof.azurewebsites.net","method":"GET","ret":"txt","url":"http://iof.azurewebsites.net/api/configuration/{{payload}}","tls":"","x":438,"y":280,"wires":[["534ecd7b.28ede4"]]}]